flask_httpcaching.py
setup.py
Flask_HttpCaching.egg-info/PKG-INFO
Flask_HttpCaching.egg-info/SOURCES.txt
Flask_HttpCaching.egg-info/dependency_links.txt
Flask_HttpCaching.egg-info/not-zip-safe
Flask_HttpCaching.egg-info/requires.txt
Flask_HttpCaching.egg-info/top_level.txt