Metadata-Version: 1.1
Name: Flask-HttpCaching
Version: 0.01
Summary: flask http caching
Home-page: http://github.com/zakzou/flask_httpcaching
Author: zakzou
Author-email: zakzou@live.com
License: MIT
Platform: any
Classifier: Environment :: Web Environment
Classifier: Intended Audience :: Developers
Classifier: License :: OSI Approved :: MIT License
Classifier: Operating System :: OS Independent
Classifier: Programming Language :: Python
Classifier: Topic :: Internet :: WWW/HTTP :: Dynamic Content
Classifier: Topic :: Software Development :: Libraries :: Python Modules
